cloudsteak-0.0.0.10.data/scripts/cloudsteak
modules/__init__.py
modules/version.py
cloudsteak-0.0.0.10.dist-info/METADATA
cloudsteak-0.0.0.10.dist-info/WHEEL
cloudsteak-0.0.0.10.dist-info/top_level.txt
cloudsteak-0.0.0.10.dist-info/zip-safe
cloudsteak-0.0.0.10.dist-info/RECORD
