Metadata-Version: 2.1
Name: cloudsteak
Version: 0.0.0.10
Summary: CloudSteak - Cloud Tools by the1bit
Home-page: https://github.com/the1bit/cloudsteak
Author: Tibor Kiss
Author-email: the1bithu@gmail.com
License: MIT
Keywords: cloud azure aws management python microsoft the1bithu
Platform: UNKNOWN
Classifier: Development Status :: 3 - Alpha
Classifier: Operating System :: Microsoft :: Windows
Classifier: Operating System :: POSIX :: Linux
Classifier: Intended Audience :: Developers
Classifier: Topic :: Software Development :: Build Tools
Classifier: License :: OSI Approved :: MIT License
Classifier: Programming Language :: Python
Classifier: Programming Language :: Python :: 2
Classifier: Programming Language :: Python :: 2.7
Requires-Python: >=2.6, <3
Requires-Dist: azure-cli
Requires-Dist: awscli
Requires-Dist: docopt
